<?xml version="1.0" encoding="UTF-8"?>
<yml_catalog date="2026-03-26T06:33:36.018+03:00">
  <shop>
    <name>Азалия</name>
    <company>azalia</company>
    <url>https://flowwow.com/moscow/shops/wholesale/</url>
    <categories>
      <category id="1">Роза одноголовая</category>
      <category id="2">Роза одноголовая пионовидная</category>
      <category id="3">Роза кустовая</category>
      <category id="4">Роза кустовая пионовидная</category>
      <category id="5">Хризантема одноголовая</category>
      <category id="6">Хризантема кустовая</category>
      <category id="7">Хризантема Сантини</category>
      <category id="37">Цветы</category>
      <category id="38">Зелень</category>
      <category id="39">Декор</category>
    </categories>
    <offers>
    <offer id="Az5415" available="true">
      <categoryId>37</categoryId>
      <name>Астильба Поп Гардер 50 см Арт. Az5415</name>
      <price>211</price>
      <qty>60</qty>
      <quantity_in_package>10</quantity_in_package>
      <picture>https://lh3.googleusercontent.com/d/1Vnwc4UWKfyCXdzINQR9HZypHLxb32gUj</picture>
      <picture>https://lh3.googleusercontent.com/d/1Z7fc90DEUpHzNs0PHFouaHusrF9BqJJ1</picture>
      <picture>https://lh3.googleusercontent.com/d/1yA3WT5q53Ep94bllBy54EX4QTUcn-O1f</picture>
      <description>ВНИМАНИЕ! Заказ возможен только целыми пачками по 10 шт.</description>
      <param name="Высота, см">50</param>
      <param name="Страна">уточняется</param>
      <param name="Артикул">Az5415</param>
      <consist name="Астильба Поп Гардер" unit="шт">10</consist>
    </offer>
    <offer id="Az3554" available="true">
      <categoryId>37</categoryId>
      <name>Хамелациум Ади 40 см Арт. Az3554</name>
      <price>256</price>
      <qty>15</qty>
      <quantity_in_package>5</quantity_in_package>
      <picture>https://lh3.googleusercontent.com/d/1GRlTNcb1gt9mtaJX5sSxFYmi9M8CAc9F</picture>
      <picture>https://lh3.googleusercontent.com/d/1lDJH7pIDlldcu7qInT2nA9aJn-St0eii</picture>
      <description>ВНИМАНИЕ! Заказ возможен только целыми пачками по 5 шт.</description>
      <param name="Высота, см">40</param>
      <param name="Страна">уточняется</param>
      <param name="Артикул">Az3554</param>
      <consist name="Хамелациум Ади" unit="шт">5</consist>
    </offer>
    </offers>
  </shop>
</yml_catalog>