<?xml version="1.0" encoding="UTF-8"?>
<yml_catalog date="2026-04-10T06:23:32.714+03:00">
  <shop>
    <name>Азалия</name>
    <company>azalia</company>
    <url>https://flowwow.com/moscow/shops/wholesale/</url>
    <categories>
      <category id="1">Роза одноголовая</category>
      <category id="2">Роза одноголовая пионовидная</category>
      <category id="3">Роза кустовая</category>
      <category id="4">Роза кустовая пионовидная</category>
      <category id="5">Хризантема одноголовая</category>
      <category id="6">Хризантема кустовая</category>
      <category id="7">Хризантема Сантини</category>
      <category id="37">Цветы</category>
      <category id="38">Зелень</category>
      <category id="39">Декор</category>
    </categories>
    <offers>
    <offer id="Az5415" available="true">
      <categoryId>37</categoryId>
      <name>Астильба Поп Гардер 50 см Арт. Az5415</name>
      <price>196</price>
      <qty>10</qty>
      <quantity_in_package>10</quantity_in_package>
      <picture>https://lh3.googleusercontent.com/d/1mcBewWcPekNm-5YmFiPcy7wrX2gUVeZ9</picture>
      <picture>https://lh3.googleusercontent.com/d/1Z7fc90DEUpHzNs0PHFouaHusrF9BqJJ1</picture>
      <picture>https://lh3.googleusercontent.com/d/1yA3WT5q53Ep94bllBy54EX4QTUcn-O1f</picture>
      <picture>https://lh3.googleusercontent.com/d/1Vnwc4UWKfyCXdzINQR9HZypHLxb32gUj</picture>
      <picture>https://lh3.googleusercontent.com/d/1KShN0Ci95QyHYQuC6-oCy79N6YhfsP6Y</picture>
      <description>ВНИМАНИЕ! Заказ возможен только целыми пачками по 10 шт.</description>
      <param name="Высота, см">50</param>
      <param name="Страна">Голландия</param>
      <param name="Артикул">Az5415</param>
      <consist name="Астильба Поп Гардер" unit="шт">10</consist>
    </offer>
    <offer id="Az3186" available="true">
      <categoryId>37</categoryId>
      <name>Ирис Фиолетовый 60 см Арт. Az3186</name>
      <price>106</price>
      <qty>350</qty>
      <quantity_in_package>25</quantity_in_package>
      <picture>https://lh3.googleusercontent.com/d/1CBorV-W5t1EnOs6STF8fOpisBrSl13BZ</picture>
      <picture>https://lh3.googleusercontent.com/d/1iWAqURrvwd39qSGieva0Ejy13_kHVNpf</picture>
      <picture>https://lh3.googleusercontent.com/d/1nB4e-H7R0Kmm2gipXDsxEdnVQ3gJ174b</picture>
      <picture>https://lh3.googleusercontent.com/d/1Pl1L3GEkp5b9HK53BVASvRBEGKWMUa7l</picture>
      <picture>https://lh3.googleusercontent.com/d/1KzFDT5EewHzrHpcIwY3ohQVjoDskdmg3</picture>
      <description>ВНИМАНИЕ! Заказ возможен только целыми пачками по 25 шт.</description>
      <param name="Высота, см">60</param>
      <param name="Страна">Россия</param>
      <param name="Артикул">Az3186</param>
      <consist name="Ирис" unit="шт">25</consist>
    </offer>
    </offers>
  </shop>
</yml_catalog>