<?xml version="1.0" encoding="UTF-8"?>
<yml_catalog date="2025-10-06T07:20:42.063+03:00">
  <shop>
    <name>Цветы оптом</name>
    <company>cvetiopt</company>
    <url>https://flowwow.com/moscow/shops/wholesale/</url>
    <categories>
      <category id="1">Роза одноголовая</category>
      <category id="2">Роза одноголовая пионовидная</category>
      <category id="3">Роза кустовая</category>
      <category id="4">Роза кустовая пионовидная</category>
      <category id="5">Хризантема одноголовая</category>
      <category id="6">Хризантема кустовая</category>
      <category id="7">Хризантема Сантини</category>
      <category id="37">Цветы</category>
      <category id="38">Зелень</category>
      <category id="39">Декор</category>
    </categories>
    <offers>
    <offer id="Cp04347" available="true">
      <categoryId>5</categoryId>
      <name>Хризантема одноголовая Оранжевый 70 см Арт. Cp04347</name>
      <price>160</price>
      <qty>10</qty>
      <quantity_in_package>10</quantity_in_package>
      <picture>https://lh3.googleusercontent.com/d/14SG6QV65SoGlqzpKQyRMpGCYOO5eNksj</picture>
      <picture>https://lh3.googleusercontent.com/d/1UzQKCy_nJvxDzFdsB1DgKhC-sI7i5IRv</picture>
      <picture>https://lh3.googleusercontent.com/d/13IA2dTpSoQ62WM9xsvZLPI4BCeTX-hlZ</picture>
      <picture>https://lh3.googleusercontent.com/d/1CFZ4CTRUBA8YjkTdt6SgzCdNspJWD0Jf</picture>
      <picture>https://lh3.googleusercontent.com/d/1nHGbg__kdrRZDNSqkyF5_UBsZmU2LUT0</picture>
      <description>ВНИМАНИЕ! Заказ возможен только целыми пачками по 10 шт.</description>
      <param name="Высота, см">70</param>
      <param name="Страна">уточняется</param>
      <param name="Артикул">Cp04347</param>
      <consist name="Хризантема одноголовая" unit="шт">10</consist>
    </offer>
    <offer id="Cp1170" available="true">
      <categoryId>37</categoryId>
      <name>Аллиум 50 см Арт. Cp1170</name>
      <price>143</price>
      <qty>15</qty>
      <quantity_in_package>15</quantity_in_package>
      <picture>https://lh3.googleusercontent.com/d/19gQqrXfJaIYQDpFjsSiMOEGaRIGiRCF7</picture>
      <picture>https://lh3.googleusercontent.com/d/1jMGFggPbLpaVILVevzeBQRH3ioxYbvd0</picture>
      <picture>https://lh3.googleusercontent.com/d/1a1Xly659CKy84IZwOwKEIHXuHlrYHcEJ</picture>
      <picture>https://lh3.googleusercontent.com/d/1VCXoH-DNzOp8ewnVwXItU9dV3RomKK7S</picture>
      <description>ВНИМАНИЕ! Заказ возможен только целыми пачками по 15 шт.</description>
      <param name="Высота, см">50</param>
      <param name="Страна">уточняется</param>
      <param name="Артикул">Cp1170</param>
      <consist name="Аллиум" unit="шт">15</consist>
    </offer>
    <offer id="Cp01665" available="true">
      <categoryId>37</categoryId>
      <name>Гентиана Синий 50 см Арт. Cp01665</name>
      <price>154</price>
      <qty>10</qty>
      <quantity_in_package>10</quantity_in_package>
      <picture>https://lh3.googleusercontent.com/d/14LiXgEZ8PoLvX6GPyGbLvBPsQjEhHFCA</picture>
      <picture>https://lh3.googleusercontent.com/d/1zvZdMAuDCocOC8uA-mrf0YMBzEuHR4R6</picture>
      <picture>https://lh3.googleusercontent.com/d/1-MVc8J0sKWfAClcnm47CJoPp8U1hmc3M</picture>
      <picture>https://lh3.googleusercontent.com/d/1gfvflW8PiMjECP4FHPMetZU4JjZ_6Eax</picture>
      <picture>https://lh3.googleusercontent.com/d/1vKybwcxxFmGMP6eJC89HoiHYnFmvLSBd</picture>
      <description>ВНИМАНИЕ! Заказ возможен только целыми пачками по 10 шт.</description>
      <param name="Высота, см">50</param>
      <param name="Страна">уточняется</param>
      <param name="Артикул">Cp01665</param>
      <consist name="Гентиана" unit="шт">10</consist>
    </offer>
    <offer id="Cp01445" available="true">
      <categoryId>37</categoryId>
      <name>Гиперикум Зеленый 50 см Арт. Cp01445</name>
      <price>105</price>
      <qty>10</qty>
      <quantity_in_package>10</quantity_in_package>
      <picture>https://lh3.googleusercontent.com/d/1fvzza5ivo7VVhe_RGMMD82TxSmOwpvbN</picture>
      <picture>https://lh3.googleusercontent.com/d/1jfqGrCL2Lwqz13dhoIU4CBf-Vxnq13nt</picture>
      <picture>https://lh3.googleusercontent.com/d/1AJ04RLZZhiDD-px1NaNq9WxRVwT7UfYS</picture>
      <picture>https://lh3.googleusercontent.com/d/1o_bjOy0ijaeQY0vqQl2KqiAnPx3khh9p</picture>
      <picture>https://lh3.googleusercontent.com/d/19lT18b25pYbUbaPNUtYf84pwlYVt3qWM</picture>
      <description>ВНИМАНИЕ! Заказ возможен только целыми пачками по 10 шт.</description>
      <param name="Высота, см">50</param>
      <param name="Страна">Голландия</param>
      <param name="Производитель">Florius Flowers</param>
      <param name="Артикул">Cp01445</param>
      <consist name="Гиперикум" unit="шт">10</consist>
    </offer>
    <offer id="Cp01935" available="true">
      <categoryId>37</categoryId>
      <name>Гипсофила Белая 50 см Арт. Cp01935</name>
      <price>83</price>
      <qty>25</qty>
      <quantity_in_package>25</quantity_in_package>
      <picture>https://lh3.googleusercontent.com/d/1ViRtHxCyM8Yg5T3rQ0ToPBDriBFvMDiq</picture>
      <picture>https://lh3.googleusercontent.com/d/1D6uMRYLjS9wAQ57UnI1sYbYg48rxr1L5</picture>
      <picture>https://lh3.googleusercontent.com/d/1NH6bVr_ucLYAMr3YKWBD-vhdlIy4Rv8y</picture>
      <picture>https://lh3.googleusercontent.com/d/1jy-WPYXx74GU27ci1I6Ag0tZQ8vtQjrf</picture>
      <picture>https://lh3.googleusercontent.com/d/1E6Cny0p8_Xc_MAcpURHAvY2oOFkpEww2</picture>
      <description>ВНИМАНИЕ! Заказ возможен только целыми пачками по 25 шт.</description>
      <param name="Высота, см">50</param>
      <param name="Страна">уточняется</param>
      <param name="Производитель">Esmeralda</param>
      <param name="Артикул">Cp01935</param>
      <consist name="Гипсофила Белая" unit="шт">25</consist>
    </offer>
    <offer id="Cp01645" available="true">
      <categoryId>37</categoryId>
      <name>Гипсофила Радужная 50 см Арт. Cp01645</name>
      <price>88</price>
      <qty>25</qty>
      <quantity_in_package>25</quantity_in_package>
      <picture>https://lh3.googleusercontent.com/d/185HrsIrfpvRs1-_DdOBRZ7xXAfgqRSN-</picture>
      <picture>https://lh3.googleusercontent.com/d/1IG4D6O8M-A-nOrbTYo4mXo80nxXRVjlg</picture>
      <picture>https://lh3.googleusercontent.com/d/1zhPZhib5E-qeKPDUsmL4lwuXk_mZj4Ri</picture>
      <picture>https://lh3.googleusercontent.com/d/1Er9atliL2lBweLmWB53q0zkq9puYVU9R</picture>
      <picture>https://lh3.googleusercontent.com/d/1cjbLIuKBhE-dMsWIKEe2Z2a3GvSJCFc7</picture>
      <description>ВНИМАНИЕ! Заказ возможен только целыми пачками по 25 шт.</description>
      <param name="Высота, см">50</param>
      <param name="Страна">уточняется</param>
      <param name="Производитель">Esmeralda</param>
      <param name="Артикул">Cp01645</param>
      <consist name="Гипсофила Радужная" unit="шт">25</consist>
    </offer>
    <offer id="Cp01925" available="true">
      <categoryId>37</categoryId>
      <name>Гипсофила Сиреневая 50 см Арт. Cp01925</name>
      <price>88</price>
      <qty>25</qty>
      <quantity_in_package>25</quantity_in_package>
      <picture>https://lh3.googleusercontent.com/d/19yPWe_9zhsiqHHvXtzAd41dPh6bh3Izi</picture>
      <picture>https://lh3.googleusercontent.com/d/1lSBt-oDTTOKBkROO3ZldgP_hB42lZWfE</picture>
      <picture>https://lh3.googleusercontent.com/d/1JDGCq2KWOrrwjbiG2sufwdDPmjbjY8GX</picture>
      <picture>https://lh3.googleusercontent.com/d/19KX0lTg81Oq784fe2NmO7xKwXZ5xrjb_</picture>
      <picture>https://lh3.googleusercontent.com/d/1oMmBu9rJCv-6Myig8BQOG5ktBINNCg_T</picture>
      <description>ВНИМАНИЕ! Заказ возможен только целыми пачками по 25 шт.</description>
      <param name="Высота, см">50</param>
      <param name="Страна">уточняется</param>
      <param name="Производитель">Esmeralda</param>
      <param name="Артикул">Cp01925</param>
      <consist name="Гипсофила Сиреневая" unit="шт">25</consist>
    </offer>
    <offer id="Cp12437" available="true">
      <categoryId>37</categoryId>
      <name>Кампанула Розовый 70 см Арт. Cp12437</name>
      <price>99</price>
      <qty>10</qty>
      <quantity_in_package>10</quantity_in_package>
      <picture>https://lh3.googleusercontent.com/d/1SQMno54ex1YXP0WW6UqKS58mBbnB0i4B</picture>
      <picture>https://lh3.googleusercontent.com/d/1xv3TZAva5GfQfRws2Dwlny5WbwghRLv_</picture>
      <picture>https://lh3.googleusercontent.com/d/1cGp5kznp9owvJ9F5S6TW3xMr73VBJbEy</picture>
      <description>ВНИМАНИЕ! Заказ возможен только целыми пачками по 10 шт.</description>
      <param name="Высота, см">70</param>
      <param name="Страна">уточняется</param>
      <param name="Производитель">De Waal Fensie</param>
      <param name="Артикул">Cp12437</param>
      <consist name="Кампанула" unit="шт">10</consist>
    </offer>
    <offer id="Cp559" available="true">
      <categoryId>37</categoryId>
      <name>Клематис Сиреневый 50 см Арт. Cp559</name>
      <price>94</price>
      <qty>10</qty>
      <quantity_in_package>10</quantity_in_package>
      <picture>https://lh3.googleusercontent.com/d/10Es0JlvSCnVyTj_rnT_cVCdOegX6zvlD</picture>
      <picture>https://lh3.googleusercontent.com/d/1nwxA0aLeac1TLpUzpMUVg-dFfWgy-GtF</picture>
      <picture>https://lh3.googleusercontent.com/d/12RId070kh1RPxpVoaRGIH29ay3Poup92</picture>
      <picture>https://lh3.googleusercontent.com/d/1lppdccKtSFGslwlhcpno-jQ38Na7Mp7J</picture>
      <picture>https://lh3.googleusercontent.com/d/1h-tCKWgA5_bJtcDktnF_WKsSXes0djg1</picture>
      <description>ВНИМАНИЕ! Заказ возможен только целыми пачками по 10 шт.</description>
      <param name="Высота, см">50</param>
      <param name="Страна">уточняется</param>
      <param name="Производитель">Marginpar</param>
      <param name="Артикул">Cp559</param>
      <consist name="Клематис" unit="шт">10</consist>
    </offer>
    <offer id="Cp0490" available="true">
      <categoryId>37</categoryId>
      <name>Краспедия Желтый 50 см Арт. Cp0490</name>
      <price>121</price>
      <qty>10</qty>
      <quantity_in_package>10</quantity_in_package>
      <picture>https://lh3.googleusercontent.com/d/1NgZZOVg82pMJDYOGk6TR-7iwInr6Z-E5</picture>
      <picture>https://lh3.googleusercontent.com/d/1j2dC3VlScz9m-8QQWPYkQRItzBdqkwFu</picture>
      <picture>https://lh3.googleusercontent.com/d/1dHmmktUHqZ3GbT6JvwbiKn5iFFRJnYxx</picture>
      <picture>https://lh3.googleusercontent.com/d/1cjyQxb-rr0mfhBgIJCU0Z_C2ICQc35LH</picture>
      <picture>https://lh3.googleusercontent.com/d/1MznnyLsM59zYumfB3vXGeqMYYlVXUF1q</picture>
      <description>ВНИМАНИЕ! Заказ возможен только целыми пачками по 10 шт.</description>
      <param name="Высота, см">50</param>
      <param name="Страна">Кения</param>
      <param name="Производитель">Beauti Line</param>
      <param name="Артикул">Cp0490</param>
      <consist name="Краспедия" unit="шт">10</consist>
    </offer>
    <offer id="Cp00695" available="true">
      <categoryId>37</categoryId>
      <name>Маттиола Желтый 50 см Арт. Cp00695</name>
      <price>138</price>
      <qty>5</qty>
      <quantity_in_package>5</quantity_in_package>
      <picture>https://lh3.googleusercontent.com/d/1dxzN0-tb7Ec5BH5XrE4SnSqiyhkXeW2m</picture>
      <picture>https://lh3.googleusercontent.com/d/1YCigbd5k8O5GZ9ttnpuQO3gr_R28iKs3</picture>
      <picture>https://lh3.googleusercontent.com/d/1eMT8_P1Si6vaJqwTsSlMHS_fI_fFnzF9</picture>
      <picture>https://lh3.googleusercontent.com/d/1lOl92V9l_4xYNjEFYY3dTZZ3x01Db_8_</picture>
      <picture>https://lh3.googleusercontent.com/d/1puvxa-QQoh7cPCULEd8fRTB5Q5QDWqJO</picture>
      <description>ВНИМАНИЕ! Заказ возможен только целыми пачками по 5 шт.</description>
      <param name="Высота, см">50</param>
      <param name="Страна">Эквадор</param>
      <param name="Артикул">Cp00695</param>
      <consist name="Маттиола" unit="шт">5</consist>
    </offer>
    <offer id="Cp6845" available="true">
      <categoryId>37</categoryId>
      <name>Маттиола Розовый 50 см Арт. Cp6845</name>
      <price>138</price>
      <qty>5</qty>
      <quantity_in_package>5</quantity_in_package>
      <picture>https://lh3.googleusercontent.com/d/174NzGa1Necl9GWGjCLoE3kUtmCbgBIsR</picture>
      <picture>https://lh3.googleusercontent.com/d/1E6sWxgRt_J8xF1aB_EXiuXoSx0rn9E_m</picture>
      <picture>https://lh3.googleusercontent.com/d/1jBAJaIWwzPzp9x2AZoypsWDAzMi9yqA-</picture>
      <picture>https://lh3.googleusercontent.com/d/1WohsitIB82_RmB6U71rP88HAR8Cf7Wwo</picture>
      <picture>https://lh3.googleusercontent.com/d/1FAPuzdTZY2Aj3J5UH1Z0N043Z-Niswz9</picture>
      <description>ВНИМАНИЕ! Заказ возможен только целыми пачками по 5 шт.</description>
      <param name="Высота, см">50</param>
      <param name="Страна">Эквадор</param>
      <param name="Артикул">Cp6845</param>
      <consist name="Маттиола" unit="шт">5</consist>
    </offer>
    <offer id="Cp0367" available="true">
      <categoryId>37</categoryId>
      <name>Орнитогалум Белый 50 см Арт. Cp0367</name>
      <price>99</price>
      <qty>10</qty>
      <quantity_in_package>10</quantity_in_package>
      <picture>https://lh3.googleusercontent.com/d/1Z7X8TFKvPeKMb5eydUo7b2NKIToMoOBr</picture>
      <picture>https://lh3.googleusercontent.com/d/1US_z1bdgcCN-idIqYxMCEb7vb-KDZPO3</picture>
      <picture>https://lh3.googleusercontent.com/d/1F9bX6RmN6AcbFnceXQFjXMJ_j16lGuFJ</picture>
      <picture>https://lh3.googleusercontent.com/d/1XoYzR635iWW-qKFM-xn-SEYGXR0CVVqj</picture>
      <picture>https://lh3.googleusercontent.com/d/1Q7nn9aLWq8sDtkV6bT1KK_ACoqfQ9Voa</picture>
      <description>ВНИМАНИЕ! Заказ возможен только целыми пачками по 10 шт.</description>
      <param name="Высота, см">50</param>
      <param name="Страна">уточняется</param>
      <param name="Производитель">Sand Pro Grovers</param>
      <param name="Артикул">Cp0367</param>
      <consist name="Орнитогалум" unit="шт">10</consist>
    </offer>
    <offer id="Cp04625" available="true">
      <categoryId>37</categoryId>
      <name>Хамелациум Белый 50 см Арт. Cp04625</name>
      <price>138</price>
      <qty>25</qty>
      <quantity_in_package>25</quantity_in_package>
      <picture>https://lh3.googleusercontent.com/d/1EZe3tjFvkdok-8LH762xWfRi1JGMzQLk</picture>
      <picture>https://lh3.googleusercontent.com/d/1Z-mm43lWvSTYcV8HEHSTeBsjlVaEFCwB</picture>
      <picture>https://lh3.googleusercontent.com/d/1wkE8z2BE5r4SnivNp_FL65y4c9UCzxlr</picture>
      <picture>https://lh3.googleusercontent.com/d/1t2feOGyCzh0t6tihPX3U5ahT40k4NBKE</picture>
      <picture>https://lh3.googleusercontent.com/d/1U9gjAzUnWXOCtjBQ1a_BhYPhEPCYY5iH</picture>
      <description>ВНИМАНИЕ! Заказ возможен только целыми пачками по 25 шт.</description>
      <param name="Высота, см">50</param>
      <param name="Страна">уточняется</param>
      <param name="Артикул">Cp04625</param>
      <consist name="Хамелациум" unit="шт">25</consist>
    </offer>
    <offer id="Cp01695" available="true">
      <categoryId>38</categoryId>
      <name>Буплерум Зеленый 50 см Арт. Cp01695</name>
      <price>72</price>
      <qty>50</qty>
      <quantity_in_package>50</quantity_in_package>
      <picture>https://lh3.googleusercontent.com/d/1lEXvpPT9FL0lBBGW0kT9V-qoCIgaduoq</picture>
      <picture>https://lh3.googleusercontent.com/d/1gRaKl5D-qkltKMmJLN7oSCpjCMfSNbyK</picture>
      <picture>https://lh3.googleusercontent.com/d/1GegdV1PZ9L3ybNUPLsiZl16n6uEcLI0S</picture>
      <picture>https://lh3.googleusercontent.com/d/1LhYicHiXHqcAW-PkImlTNU8FkMaW3lBr</picture>
      <picture>https://lh3.googleusercontent.com/d/1F0aGWw_AVd-9SAASfeS5AZn2P5eSCEl1</picture>
      <description>ВНИМАНИЕ! Заказ возможен только целыми пачками по 50 шт.</description>
      <param name="Высота, см">50</param>
      <param name="Страна">уточняется</param>
      <param name="Производитель">Summer Flora</param>
      <param name="Артикул">Cp01695</param>
      <consist name="Буплерум" unit="шт">50</consist>
    </offer>
    <offer id="Cp0466" available="true">
      <categoryId>38</categoryId>
      <name>Вибурнум Зеленый 50 см Арт. Cp0466</name>
      <price>424</price>
      <qty>10</qty>
      <quantity_in_package>10</quantity_in_package>
      <picture>https://lh3.googleusercontent.com/d/1rc2t9jB2wbANdll8QfU6k-6oXQxfiwnL</picture>
      <picture>https://lh3.googleusercontent.com/d/1WWLo1GWND6I9xK1h2llL8-tOl7G1DZbP</picture>
      <picture>https://lh3.googleusercontent.com/d/1frxnkl251Xi20JE7wsYwH8YAvPGDkJTi</picture>
      <picture>https://lh3.googleusercontent.com/d/1jUsUj96XXC1Xvr5Z3GEZfDL7I1GX2qg0</picture>
      <picture>https://lh3.googleusercontent.com/d/1deBW-lKzp-EgrQ1XuiNYrM3FcA9PPgw-</picture>
      <description>ВНИМАНИЕ! Заказ возможен только целыми пачками по 10 шт.</description>
      <param name="Высота, см">50</param>
      <param name="Страна">уточняется</param>
      <param name="Производитель">Filius Noordaw</param>
      <param name="Артикул">Cp0466</param>
      <consist name="Вибурнум" unit="шт">10</consist>
    </offer>
    <offer id="Cp0359" available="true">
      <categoryId>38</categoryId>
      <name>Клематис Белый 50 см Арт. Cp0359</name>
      <price>94</price>
      <qty>10</qty>
      <quantity_in_package>10</quantity_in_package>
      <picture>https://lh3.googleusercontent.com/d/1zTOo5iN1sYRnda3g0LVoKPcyWwQaI6Mo</picture>
      <picture>https://lh3.googleusercontent.com/d/1pssYT0PPYshUR4NXYqAUejGvStxvGVX6</picture>
      <picture>https://lh3.googleusercontent.com/d/1NC5yrFT1mHLn7QZ4UOEykjAnNTyOZbwI</picture>
      <picture>https://lh3.googleusercontent.com/d/19nxcbSfoJdlompqPpTXqsZ8BaeTzYIee</picture>
      <picture>https://lh3.googleusercontent.com/d/1m3bKldCi-4rIYWCNDybTKBAoiL-qdjNN</picture>
      <description>ВНИМАНИЕ! Заказ возможен только целыми пачками по 10 шт.</description>
      <param name="Высота, см">50</param>
      <param name="Страна">уточняется</param>
      <param name="Производитель">Marginpar</param>
      <param name="Артикул">Cp0359</param>
      <consist name="Клематис" unit="шт">10</consist>
    </offer>
    <offer id="Cp8215" available="true">
      <categoryId>38</categoryId>
      <name>Книп Оранжевый 50 см Арт. Cp8215</name>
      <price>138</price>
      <qty>5</qty>
      <quantity_in_package>5</quantity_in_package>
      <picture>https://lh3.googleusercontent.com/d/1k7dfMaoGoCSxSi1yua_6uSgVDV2LKH9s</picture>
      <picture>https://lh3.googleusercontent.com/d/1z_jiN1nnApboruxskjhjJT-ro9QdH9zZ</picture>
      <picture>https://lh3.googleusercontent.com/d/1I00xTPSYbVbo9ifHmc3stVLbMlV1IcL0</picture>
      <picture>https://lh3.googleusercontent.com/d/1jdcsFqs5fZHqy2Y00AjlPUNE6oOh15Mo</picture>
      <picture>https://lh3.googleusercontent.com/d/1uIYQJjNbXGiMmZlOLYecOM6hzPepTQn_</picture>
      <description>ВНИМАНИЕ! Заказ возможен только целыми пачками по 5 шт.</description>
      <param name="Высота, см">50</param>
      <param name="Страна">уточняется</param>
      <param name="Артикул">Cp8215</param>
      <consist name="Книп" unit="шт">5</consist>
    </offer>
    <offer id="Cp01686" available="true">
      <categoryId>38</categoryId>
      <name>Молюцелла Зеленый 60 см Арт. Cp01686</name>
      <price>132</price>
      <qty>10</qty>
      <quantity_in_package>10</quantity_in_package>
      <picture>https://lh3.googleusercontent.com/d/1PI2ecnD5aIp5pYPF3pxJHOGdJvrTB4fq</picture>
      <picture>https://lh3.googleusercontent.com/d/1SH5ue7eXFrJwiOTMHjilOMdoWX53M8kJ</picture>
      <picture>https://lh3.googleusercontent.com/d/1UyGAdqOhh6ugBoWQYyCQTNZSAsBSB25b</picture>
      <picture>https://lh3.googleusercontent.com/d/18EWw55ftSIh79hBf0TeJAh8lgz6t0iwH</picture>
      <picture>https://lh3.googleusercontent.com/d/19hlaOlnHCwbTMmQyGh2j6vH2U1x2qiOY</picture>
      <description>ВНИМАНИЕ! Заказ возможен только целыми пачками по 10 шт.</description>
      <param name="Высота, см">60</param>
      <param name="Страна">уточняется</param>
      <param name="Артикул">Cp01686</param>
      <consist name="Молюцелла" unit="шт">10</consist>
    </offer>
    <offer id="Cp0454" available="true">
      <categoryId>38</categoryId>
      <name>Паникум Зелёный 50 см Арт. Cp0454</name>
      <price>50</price>
      <qty>25</qty>
      <quantity_in_package>25</quantity_in_package>
      <picture>https://lh3.googleusercontent.com/d/1MFL2-fFvQtzVGnNPjUAxdlJWlQfmsqFf</picture>
      <picture>https://lh3.googleusercontent.com/d/1SIeBlapqMujjISN0Q53LGC2zDJpbu6rR</picture>
      <picture>https://lh3.googleusercontent.com/d/1UBLOul3ALHCui4UJ1HpSaXdtn-nO2g1Q</picture>
      <picture>https://lh3.googleusercontent.com/d/1fwnpPwPTe-cE3ybxm--oWWyGR2g1NDgO</picture>
      <picture>https://lh3.googleusercontent.com/d/1edweN6G2NvJakK87H5hAuUYZGMp7eACU</picture>
      <description>ВНИМАНИЕ! Заказ возможен только целыми пачками по 25 шт.</description>
      <param name="Высота, см">50</param>
      <param name="Страна">уточняется</param>
      <param name="Артикул">Cp0454</param>
      <consist name="Паникум" unit="шт">25</consist>
    </offer>
    <offer id="Cp05025" available="true">
      <categoryId>38</categoryId>
      <name>Сетария Зеленый 50 см Арт. Cp05025</name>
      <price>33</price>
      <qty>10</qty>
      <quantity_in_package>10</quantity_in_package>
      <picture>https://lh3.googleusercontent.com/d/11AUWqz1X2DFPB4Y5-JhNs_lg8o5uNCXM</picture>
      <picture>https://lh3.googleusercontent.com/d/15jIQHoVM9G-yB2vG-EWfWW2Qjvb3LUQQ</picture>
      <picture>https://lh3.googleusercontent.com/d/1mI3KBhUrJ-lJTcJ4EJne3MSETihRPrQa</picture>
      <picture>https://lh3.googleusercontent.com/d/1LkHaRh5RNng_CTEPov9a0lnRr2jgkbi4</picture>
      <picture>https://lh3.googleusercontent.com/d/1knWvdRhE-k588fT098nOtIYVjwyvE6td</picture>
      <description>ВНИМАНИЕ! Заказ возможен только целыми пачками по 10 шт.</description>
      <param name="Высота, см">50</param>
      <param name="Страна">уточняется</param>
      <param name="Артикул">Cp05025</param>
      <consist name="Сетария" unit="шт">10</consist>
    </offer>
    <offer id="Cp04056" available="true">
      <categoryId>38</categoryId>
      <name>Симфорикарпус Белый 60 см Арт. Cp04056</name>
      <price>110</price>
      <qty>10</qty>
      <quantity_in_package>10</quantity_in_package>
      <picture>https://lh3.googleusercontent.com/d/1u2kft452EoxXhEp_vyi6_UDBY0ok2sLV</picture>
      <picture>https://lh3.googleusercontent.com/d/1E0vjLGadcdkcV_unxvmsx_Wa40g7RZTh</picture>
      <picture>https://lh3.googleusercontent.com/d/1bTzpiR94Lcg2YXNrHNOOg4q-ZLweLWdl</picture>
      <picture>https://lh3.googleusercontent.com/d/120nobNbG8jrANGUxYhUuRJi1Utb-ZB85</picture>
      <picture>https://lh3.googleusercontent.com/d/1w9SBjFbVdxq4dLdju4fwuGoMPXj3rWtw</picture>
      <description>ВНИМАНИЕ! Заказ возможен только целыми пачками по 10 шт.</description>
      <param name="Высота, см">60</param>
      <param name="Страна">уточняется</param>
      <param name="Артикул">Cp04056</param>
      <consist name="Симфорикарпус" unit="шт">10</consist>
    </offer>
    <offer id="Cp01705" available="true">
      <categoryId>38</categoryId>
      <name>Солидаго Желтый 50 см Арт. Cp01705</name>
      <price>94</price>
      <qty>25</qty>
      <quantity_in_package>25</quantity_in_package>
      <picture>https://lh3.googleusercontent.com/d/1NWGlehGAdrcZdom-61JGUOd6E0mZE9bI</picture>
      <picture>https://lh3.googleusercontent.com/d/1i71EVt7_gA3RzCWi5ombdSrb7s548Ucr</picture>
      <picture>https://lh3.googleusercontent.com/d/1vBwftSCW2vyL0Y2bXjtXlQCFbVmHqU5J</picture>
      <picture>https://lh3.googleusercontent.com/d/1QENGo4vB6XoJKW891nrhbZLDXYRNHE7V</picture>
      <picture>https://lh3.googleusercontent.com/d/1GM1AKgIXXbD4vSlhbogZL4O88zDzF9_n</picture>
      <description>ВНИМАНИЕ! Заказ возможен только целыми пачками по 25 шт.</description>
      <param name="Высота, см">50</param>
      <param name="Страна">уточняется</param>
      <param name="Производитель">Marginpar</param>
      <param name="Артикул">Cp01705</param>
      <consist name="Солидаго" unit="шт">25</consist>
    </offer>
    <offer id="Cp1082" available="true">
      <categoryId>38</categoryId>
      <name>Тласпи 50 см Арт. Cp1082</name>
      <price>99</price>
      <qty>40</qty>
      <quantity_in_package>40</quantity_in_package>
      <picture>https://lh3.googleusercontent.com/d/1B0zmDKJaECYjfJLdMyZsaCLmQNtV5SOu</picture>
      <picture>https://lh3.googleusercontent.com/d/1AVL-PV-YADRgo2Ef3Y5bXXVU-ayy4bwL</picture>
      <picture>https://lh3.googleusercontent.com/d/13jo3BnBbk9EdTzrB9xe4eP96s6Jm_S9d</picture>
      <picture>https://lh3.googleusercontent.com/d/1fVUEzCzklc35Jq-k2cEysfl3r3Tmcdwx</picture>
      <picture>https://lh3.googleusercontent.com/d/1nGw2Ql4zyyjcn1k0Weyqo2fu5I7hFjBy</picture>
      <description>ВНИМАНИЕ! Заказ возможен только целыми пачками по 40 шт.</description>
      <param name="Высота, см">50</param>
      <param name="Страна">уточняется</param>
      <param name="Производитель">Beauty line</param>
      <param name="Артикул">Cp1082</param>
      <consist name="Тласпи" unit="шт">40</consist>
    </offer>
    <offer id="Cp01975" available="true">
      <categoryId>38</categoryId>
      <name>Эрингиум Синий 50 см Арт. Cp01975</name>
      <price>154</price>
      <qty>10</qty>
      <quantity_in_package>10</quantity_in_package>
      <picture>https://lh3.googleusercontent.com/d/1vbbNEBn8jcA-tNILCI6yx-cMDXWv__sa</picture>
      <picture>https://lh3.googleusercontent.com/d/1fyVIYs6UAsacfeRcTkFayM8w3KTco_o4</picture>
      <picture>https://lh3.googleusercontent.com/d/1fcOyZ-0abmyTLbNufqo4DZ87sfGvyAGU</picture>
      <picture>https://lh3.googleusercontent.com/d/1f8DjAGUEjV6H-iedFZYfW0z9wAUHqWiU</picture>
      <picture>https://lh3.googleusercontent.com/d/1vpM9cG72Le0BrIotUnUo2T5TOjOPmzVN</picture>
      <description>ВНИМАНИЕ! Заказ возможен только целыми пачками по 10 шт.</description>
      <param name="Высота, см">50</param>
      <param name="Страна">уточняется</param>
      <param name="Производитель">Marginpar</param>
      <param name="Артикул">Cp01975</param>
      <consist name="Эрингиум" unit="шт">10</consist>
    </offer>
    </offers>
  </shop>
</yml_catalog>