<?xml version="1.0" encoding="UTF-8"?>
<yml_catalog date="2026-03-20T02:17:15.718+03:00">
  <shop>
    <name>West flora</name>
    <company>westflora</company>
    <url>https://flowwow.com/moscow/shops/wholesale/</url>
    <categories>
      <category id="450">Цветы пачками</category>
    </categories>
    <offers>
    <offer id="Va1716c" available="true">
      <name>Пачка (10 шт.) Роза кустовая Бандолеро 60 см Арт. Va1716c</name>
      <categoryId>450</categoryId>
      <price>3902</price>
      <qty>4</qty>
      <picture>https://lh3.googleusercontent.com/d/1vpIWe7dh2YNyIGTfxtUPDbTxLD_VYwyD</picture>
      <picture>https://lh3.googleusercontent.com/d/1Z2r9kG_X0Zo4-Ocg1e0NeKYeqA_C6Tpp</picture>
      <picture>https://lh3.googleusercontent.com/d/1iujvyB2SBwe4hv4yf0k1BZPmDlDNwlEB</picture>
      <description>Пачки — новый формат для тех, кто хочет максимум свежести и аромата. Свежесрезанные цветы прямо из теплицы: без услуг флориста и лишней упаковки — выгодно и просто. Формат: пачка 10 стеблей; можно заказать несколько пачек. Открытка, сборка букета и добавление отдельных стеблей не предусмотрены. *Цветы доставляются без дополнительной обработки флористом — сохраняем их естественный вид.</description>
      <param name="Высота, см">60</param>
      <param name="Ширина, см">15</param>
      <param name="Страна">Эфиопия</param>
      <param name="Производитель">Braam Born to Bloom</param>
      <param name="Артикул">Va1716c</param>
      <consist name="Роза кустовая Бандолеро" unit="шт">10</consist>
    </offer>
    <offer id="Va1756c" available="true">
      <name>Пачка (10 шт.) Роза кустовая Фаер Флоу 60 см Арт. Va1756c</name>
      <categoryId>450</categoryId>
      <price>3902</price>
      <qty>4</qty>
      <picture>https://lh3.googleusercontent.com/d/1usebM9vi4SfKR3vaGqQzHQ89ALO2MxC9</picture>
      <picture>https://lh3.googleusercontent.com/d/1AVDMTwVVeBGbE65XprYUQM5cCoTTpkSm</picture>
      <picture>https://lh3.googleusercontent.com/d/1OZfaDlUX6EsrMAMp_-ICRjM_014as1VF</picture>
      <description>Пачки — новый формат для тех, кто хочет максимум свежести и аромата. Свежесрезанные цветы прямо из теплицы: без услуг флориста и лишней упаковки — выгодно и просто. Формат: пачка 10 стеблей; можно заказать несколько пачек. Открытка, сборка букета и добавление отдельных стеблей не предусмотрены. *Цветы доставляются без дополнительной обработки флористом — сохраняем их естественный вид.</description>
      <param name="Высота, см">60</param>
      <param name="Ширина, см">15</param>
      <param name="Страна">Кения</param>
      <param name="Производитель">Flora Ola</param>
      <param name="Артикул">Va1756c</param>
      <consist name="Роза кустовая Фаер Флоу" unit="шт">10</consist>
    </offer>
    <offer id="Va3527c" available="true">
      <name>Пачка (10 шт.) Хризантема одноголовая Момоко 70 см Арт. Va3527c</name>
      <categoryId>450</categoryId>
      <price>3363</price>
      <qty>2</qty>
      <picture>https://lh3.googleusercontent.com/d/1qw4Bcs9uX4buFCLjDcVvO21a4m064DJk</picture>
      <picture>https://lh3.googleusercontent.com/d/1hf4NQ4rDcZwihSvaTTFNNmtO0EA8Sdfz</picture>
      <picture>https://lh3.googleusercontent.com/d/1P0fZ5lwBkrUErI0skSwk4tSEByH4hyHg</picture>
      <description>Пачки — новый формат для тех, кто хочет максимум свежести и аромата. Свежесрезанные цветы прямо из теплицы: без услуг флориста и лишней упаковки — выгодно и просто. Формат: пачка 10 стеблей; можно заказать несколько пачек. Открытка, сборка букета и добавление отдельных стеблей не предусмотрены. *Цветы доставляются без дополнительной обработки флористом — сохраняем их естественный вид.</description>
      <param name="Высота, см">70</param>
      <param name="Ширина, см">15</param>
      <param name="Страна">Голландия</param>
      <param name="Производитель">Decorum</param>
      <param name="Артикул">Va3527c</param>
      <consist name="Хризантема одноголовая Момоко" unit="шт">10</consist>
    </offer>
    <offer id="Va2127c" available="true">
      <name>Пачка (10 шт.) Хризантема одноголовая Супербоул 70 см Арт. Va2127c</name>
      <categoryId>450</categoryId>
      <price>3363</price>
      <qty>1</qty>
      <picture>https://lh3.googleusercontent.com/d/1PhT6iHbLnFQkjKNr-qeftLQl2TZgVcPm</picture>
      <picture>https://lh3.googleusercontent.com/d/1-bbgykNSjFI822jQM536YSc1x5AE2MnX</picture>
      <picture>https://lh3.googleusercontent.com/d/1JK0FuXQfGJMXRwc2iGTBRUcVLKxbqjvT</picture>
      <description>Пачки — новый формат для тех, кто хочет максимум свежести и аромата. Свежесрезанные цветы прямо из теплицы: без услуг флориста и лишней упаковки — выгодно и просто. Формат: пачка 10 стеблей; можно заказать несколько пачек. Открытка, сборка букета и добавление отдельных стеблей не предусмотрены. *Цветы доставляются без дополнительной обработки флористом — сохраняем их естественный вид.</description>
      <param name="Высота, см">70</param>
      <param name="Ширина, см">15</param>
      <param name="Страна">Голландия</param>
      <param name="Производитель">Zentoo</param>
      <param name="Артикул">Va2127c</param>
      <consist name="Хризантема одноголовая Супербоул" unit="шт">10</consist>
    </offer>
    <offer id="Va2217c" available="true">
      <name>Пачка (5 шт.) Хризантема кустовая Алтай 70 см Арт. Va2217c</name>
      <categoryId>450</categoryId>
      <price>1523</price>
      <qty>7</qty>
      <picture>https://lh3.googleusercontent.com/d/1hlHyksDsiuUsrmi1ynAoM2F8PxJOusZI</picture>
      <picture>https://lh3.googleusercontent.com/d/1gyRMO9q8R3RasgXvjACxODN7yrfWL7gn</picture>
      <picture>https://lh3.googleusercontent.com/d/1xCKQdDKtH0IXXB6cHszZRKG6G5z2g89Z</picture>
      <description>Пачки — новый формат для тех, кто хочет максимум свежести и аромата. Свежесрезанные цветы прямо из теплицы: без услуг флориста и лишней упаковки — выгодно и просто. Формат: пачка 5 стеблей; можно заказать несколько пачек. Открытка, сборка букета и добавление отдельных стеблей не предусмотрены. *Цветы доставляются без дополнительной обработки флористом — сохраняем их естественный вид.</description>
      <param name="Высота, см">70</param>
      <param name="Ширина, см">15</param>
      <param name="Страна">Голландия</param>
      <param name="Производитель">VannoVa</param>
      <param name="Артикул">Va2217c</param>
      <consist name="Хризантема кустовая Алтай" unit="шт">5</consist>
    </offer>
    <offer id="Va0346c" available="true">
      <name>Пачка (5 шт.) Хризантема кустовая Алтай Еллоу 60 см Арт. Va0346c</name>
      <categoryId>450</categoryId>
      <price>1523</price>
      <qty>6</qty>
      <picture>https://lh3.googleusercontent.com/d/1uffEgIhXiNG_VE4xclA3W24zMOZuO2j0</picture>
      <picture>https://lh3.googleusercontent.com/d/1JVSM5IzgfqpoMFnDu3bl5hVDr7YfvP5o</picture>
      <picture>https://lh3.googleusercontent.com/d/12DhpjQ9JRvmBXBiAQI6yYeXMZ3xIrikN</picture>
      <description>Пачки — новый формат для тех, кто хочет максимум свежести и аромата. Свежесрезанные цветы прямо из теплицы: без услуг флориста и лишней упаковки — выгодно и просто. Формат: пачка 5 стеблей; можно заказать несколько пачек. Открытка, сборка букета и добавление отдельных стеблей не предусмотрены. *Цветы доставляются без дополнительной обработки флористом — сохраняем их естественный вид.</description>
      <param name="Высота, см">60</param>
      <param name="Ширина, см">15</param>
      <param name="Страна">Голландия</param>
      <param name="Производитель">Zentoo</param>
      <param name="Артикул">Va0346c</param>
      <consist name="Хризантема кустовая Алтай Еллоу" unit="шт">5</consist>
    </offer>
    <offer id="Va0806c" available="true">
      <name>Пачка (5 шт.) Хризантема кустовая Алтай Еллоу 60 см Арт. Va0806c</name>
      <categoryId>450</categoryId>
      <price>1523</price>
      <qty>6</qty>
      <picture>https://lh3.googleusercontent.com/d/1BV9W23rei4c1TASd4ygWE10K5bWYkO79</picture>
      <picture>https://lh3.googleusercontent.com/d/1AYOEI9_KcCftwrbcebPPxlxknoRVhwtx</picture>
      <picture>https://lh3.googleusercontent.com/d/1J5M-974Udosw5m4IZ37KCU4rag8o57Yl</picture>
      <description>Пачки — новый формат для тех, кто хочет максимум свежести и аромата. Свежесрезанные цветы прямо из теплицы: без услуг флориста и лишней упаковки — выгодно и просто. Формат: пачка 5 стеблей; можно заказать несколько пачек. Открытка, сборка букета и добавление отдельных стеблей не предусмотрены. *Цветы доставляются без дополнительной обработки флористом — сохраняем их естественный вид.</description>
      <param name="Высота, см">60</param>
      <param name="Ширина, см">15</param>
      <param name="Страна">Голландия</param>
      <param name="Производитель">Zentoo</param>
      <param name="Артикул">Va0806c</param>
      <consist name="Хризантема кустовая Алтай Еллоу" unit="шт">5</consist>
    </offer>
    <offer id="Va0877c" available="true">
      <name>Пачка (5 шт.) Хризантема кустовая Бейби 70 см Арт. Va0877c</name>
      <categoryId>450</categoryId>
      <price>1433</price>
      <qty>7</qty>
      <picture>https://lh3.googleusercontent.com/d/1_P9En0GjpjRVI_XLFF4I1HmM5vl5U4et</picture>
      <picture>https://lh3.googleusercontent.com/d/1RK0lt5ehXhxdI5j6wmCN1mussz05tBzl</picture>
      <picture>https://lh3.googleusercontent.com/d/1u3miTdcBOJFqjQ9AglS1f6Sw9iyLnWXr</picture>
      <description>Пачки — новый формат для тех, кто хочет максимум свежести и аромата. Свежесрезанные цветы прямо из теплицы: без услуг флориста и лишней упаковки — выгодно и просто. Формат: пачка 5 стеблей; можно заказать несколько пачек. Открытка, сборка букета и добавление отдельных стеблей не предусмотрены. *Цветы доставляются без дополнительной обработки флористом — сохраняем их естественный вид.</description>
      <param name="Высота, см">70</param>
      <param name="Ширина, см">15</param>
      <param name="Страна">Голландия</param>
      <param name="Производитель">Zentoo</param>
      <param name="Артикул">Va0877c</param>
      <consist name="Хризантема кустовая Бейби" unit="шт">5</consist>
    </offer>
    <offer id="Va3917c" available="true">
      <name>Пачка (5 шт.) Хризантема кустовая Бонтемпи 70 см Арт. Va3917c</name>
      <categoryId>450</categoryId>
      <price>1433</price>
      <qty>7</qty>
      <picture>https://lh3.googleusercontent.com/d/1p4lBN6DEjsG1GM0PWBO4Td-c4RsUG0Bu</picture>
      <picture>https://lh3.googleusercontent.com/d/1ofHe_J8cL1ELvRqsQJ3a-AxHcsM-8rYl</picture>
      <description>Пачки — новый формат для тех, кто хочет максимум свежести и аромата. Свежесрезанные цветы прямо из теплицы: без услуг флориста и лишней упаковки — выгодно и просто. Формат: пачка 5 стеблей; можно заказать несколько пачек. Открытка, сборка букета и добавление отдельных стеблей не предусмотрены. *Цветы доставляются без дополнительной обработки флористом — сохраняем их естественный вид.</description>
      <param name="Высота, см">70</param>
      <param name="Ширина, см">15</param>
      <param name="Страна">Голландия</param>
      <param name="Артикул">Va3917c</param>
      <consist name="Хризантема кустовая Бонтемпи" unit="шт">5</consist>
    </offer>
    <offer id="Va0707c" available="true">
      <name>Пачка (5 шт.) Хризантема кустовая Делегрин 70 см Арт. Va0707c</name>
      <categoryId>450</categoryId>
      <price>1433</price>
      <qty>8</qty>
      <picture>https://lh3.googleusercontent.com/d/1niTx87rLPS7ImP4h1e8WIDsueHrYy8Zp</picture>
      <picture>https://lh3.googleusercontent.com/d/1JmnzXayngqyfW4R9l1Wxj1uAo7XqC6GA</picture>
      <picture>https://lh3.googleusercontent.com/d/16iF-TFxmW7XJeyG_9fGoUVj4Vp3xr4VW</picture>
      <description>Пачки — новый формат для тех, кто хочет максимум свежести и аромата. Свежесрезанные цветы прямо из теплицы: без услуг флориста и лишней упаковки — выгодно и просто. Формат: пачка 5 стеблей; можно заказать несколько пачек. Открытка, сборка букета и добавление отдельных стеблей не предусмотрены. *Цветы доставляются без дополнительной обработки флористом — сохраняем их естественный вид.</description>
      <param name="Высота, см">70</param>
      <param name="Ширина, см">15</param>
      <param name="Страна">Голландия</param>
      <param name="Производитель">Zentoo</param>
      <param name="Артикул">Va0707c</param>
      <consist name="Хризантема кустовая Делегрин" unit="шт">5</consist>
    </offer>
    <offer id="Va2967c" available="true">
      <name>Пачка (5 шт.) Хризантема кустовая Кеннеди 70 см Арт. Va2967c</name>
      <categoryId>450</categoryId>
      <price>1433</price>
      <qty>5</qty>
      <picture>https://lh3.googleusercontent.com/d/1CkDuc3SLHbUSEl8efLqtnpUZrIIL-Ehn</picture>
      <picture>https://lh3.googleusercontent.com/d/1iYGFvVB84l0el-P2URkA3EuJGWXkw6Ny</picture>
      <picture>https://lh3.googleusercontent.com/d/1jputGXmEtOn7IJFl7RvgQzOwNmrWOBaf</picture>
      <description>Пачки — новый формат для тех, кто хочет максимум свежести и аромата. Свежесрезанные цветы прямо из теплицы: без услуг флориста и лишней упаковки — выгодно и просто. Формат: пачка 5 стеблей; можно заказать несколько пачек. Открытка, сборка букета и добавление отдельных стеблей не предусмотрены. *Цветы доставляются без дополнительной обработки флористом — сохраняем их естественный вид.</description>
      <param name="Высота, см">70</param>
      <param name="Ширина, см">15</param>
      <param name="Страна">Голландия</param>
      <param name="Производитель">VannoVa</param>
      <param name="Артикул">Va2967c</param>
      <consist name="Хризантема кустовая Кеннеди" unit="шт">5</consist>
    </offer>
    <offer id="Va1967c" available="true">
      <name>Пачка (5 шт.) Хризантема кустовая Оптимист 70 см Арт. Va1967c</name>
      <categoryId>450</categoryId>
      <price>1433</price>
      <qty>8</qty>
      <picture>https://lh3.googleusercontent.com/d/12d7qf8ImxnOmKCUesMFGBr5_AZwOkBFU</picture>
      <picture>https://lh3.googleusercontent.com/d/1XhpCWdIY5mfYTd4b70JXNxVK09uT39vg</picture>
      <picture>https://lh3.googleusercontent.com/d/1xEpWfoD3hmxFo51LrtSom9L0_zlX7LvA</picture>
      <description>Пачки — новый формат для тех, кто хочет максимум свежести и аромата. Свежесрезанные цветы прямо из теплицы: без услуг флориста и лишней упаковки — выгодно и просто. Формат: пачка 5 стеблей; можно заказать несколько пачек. Открытка, сборка букета и добавление отдельных стеблей не предусмотрены. *Цветы доставляются без дополнительной обработки флористом — сохраняем их естественный вид.</description>
      <param name="Высота, см">70</param>
      <param name="Ширина, см">15</param>
      <param name="Страна">Голландия</param>
      <param name="Производитель">Decorum</param>
      <param name="Артикул">Va1967c</param>
      <consist name="Хризантема кустовая Оптимист" unit="шт">5</consist>
    </offer>
    <offer id="Va0366c" available="true">
      <name>Пачка (5 шт.) Хризантема кустовая Пастела Пинк 60 см Арт. Va0366c</name>
      <categoryId>450</categoryId>
      <price>1433</price>
      <qty>6</qty>
      <picture>https://lh3.googleusercontent.com/d/14y5aftEJ7KiL-SLsn8zkY4vVgT5p9YtA</picture>
      <picture>https://lh3.googleusercontent.com/d/1IOp2ZXKHPUzjgZY_YQdHTQKs3dZvwbYa</picture>
      <picture>https://lh3.googleusercontent.com/d/1leRVTRJyuIDzBQpSUfNG5cazPjaBCjLq</picture>
      <description>Пачки — новый формат для тех, кто хочет максимум свежести и аромата. Свежесрезанные цветы прямо из теплицы: без услуг флориста и лишней упаковки — выгодно и просто. Формат: пачка 5 стеблей; можно заказать несколько пачек. Открытка, сборка букета и добавление отдельных стеблей не предусмотрены. *Цветы доставляются без дополнительной обработки флористом — сохраняем их естественный вид.</description>
      <param name="Высота, см">60</param>
      <param name="Ширина, см">15</param>
      <param name="Страна">Голландия</param>
      <param name="Производитель">Zentoo</param>
      <param name="Артикул">Va0366c</param>
      <consist name="Хризантема кустовая Пастела Пинк" unit="шт">5</consist>
    </offer>
    <offer id="Va0667c" available="true">
      <name>Пачка (5 шт.) Хризантема кустовая Перпл Стар 70 см Арт. Va0667c</name>
      <categoryId>450</categoryId>
      <price>1433</price>
      <qty>8</qty>
      <picture>https://lh3.googleusercontent.com/d/1JxRKBt07iFhH7zOYyFpI9X24JEWe9qqi</picture>
      <picture>https://lh3.googleusercontent.com/d/1b4m41aDQE9BKPJ90brpotcPHUa-GVfx7</picture>
      <picture>https://lh3.googleusercontent.com/d/10Nwtsl6qnZuVn9TvX_IrOnbDrYF96qH9</picture>
      <description>Пачки — новый формат для тех, кто хочет максимум свежести и аромата. Свежесрезанные цветы прямо из теплицы: без услуг флориста и лишней упаковки — выгодно и просто. Формат: пачка 5 стеблей; можно заказать несколько пачек. Открытка, сборка букета и добавление отдельных стеблей не предусмотрены. *Цветы доставляются без дополнительной обработки флористом — сохраняем их естественный вид.</description>
      <param name="Высота, см">70</param>
      <param name="Ширина, см">15</param>
      <param name="Страна">Голландия</param>
      <param name="Производитель">Zentoo</param>
      <param name="Артикул">Va0667c</param>
      <consist name="Хризантема кустовая Перпл Стар" unit="шт">5</consist>
    </offer>
    <offer id="Va0717c" available="true">
      <name>Пачка (5 шт.) Хризантема кустовая Руби Стар 70 см Арт. Va0717c</name>
      <categoryId>450</categoryId>
      <price>1433</price>
      <qty>4</qty>
      <picture>https://lh3.googleusercontent.com/d/1abYkBcKMOSbIsosozcl5BsP_-dYCEl0K</picture>
      <picture>https://lh3.googleusercontent.com/d/1Xl0o0iwWLB56MlquqVXU4160pCx-3oqC</picture>
      <picture>https://lh3.googleusercontent.com/d/1W5xzm58mMDRmt_vL-KlRhCMzWjMBhU2K</picture>
      <description>Пачки — новый формат для тех, кто хочет максимум свежести и аромата. Свежесрезанные цветы прямо из теплицы: без услуг флориста и лишней упаковки — выгодно и просто. Формат: пачка 5 стеблей; можно заказать несколько пачек. Открытка, сборка букета и добавление отдельных стеблей не предусмотрены. *Цветы доставляются без дополнительной обработки флористом — сохраняем их естественный вид.</description>
      <param name="Высота, см">70</param>
      <param name="Ширина, см">15</param>
      <param name="Страна">Голландия</param>
      <param name="Производитель">Zentoo</param>
      <param name="Артикул">Va0717c</param>
      <consist name="Хризантема кустовая Руби Стар" unit="шт">5</consist>
    </offer>
    <offer id="Va1327c" available="true">
      <name>Пачка (5 шт.) Хризантема кустовая Селебрейт 70 см Арт. Va1327c</name>
      <categoryId>450</categoryId>
      <price>1433</price>
      <qty>5</qty>
      <picture>https://lh3.googleusercontent.com/d/1cMyDnIXA1hze7ZU4wnwNoKu_Cr-6TjHz</picture>
      <picture>https://lh3.googleusercontent.com/d/1gqfXATfg3eY8f3z0E42OTMzpCs78Pluc</picture>
      <picture>https://lh3.googleusercontent.com/d/1l_lgaxRvcnXargid6J4qgLXGCv_qhQGX</picture>
      <description>Пачки — новый формат для тех, кто хочет максимум свежести и аромата. Свежесрезанные цветы прямо из теплицы: без услуг флориста и лишней упаковки — выгодно и просто. Формат: пачка 5 стеблей; можно заказать несколько пачек. Открытка, сборка букета и добавление отдельных стеблей не предусмотрены. *Цветы доставляются без дополнительной обработки флористом — сохраняем их естественный вид.</description>
      <param name="Высота, см">70</param>
      <param name="Ширина, см">15</param>
      <param name="Страна">Голландия</param>
      <param name="Производитель">Zentoo</param>
      <param name="Артикул">Va1327c</param>
      <consist name="Хризантема кустовая Селебрейт" unit="шт">5</consist>
    </offer>
    <offer id="Va0105c" available="true">
      <name>Пачка (25 шт.) Хризантема Сантини Росси Пинк 55 см Арт. Va0105c</name>
      <categoryId>450</categoryId>
      <price>4933</price>
      <qty>6</qty>
      <picture>https://lh3.googleusercontent.com/d/1WgHsJ3fJI3HGPOoRXZhE7dWAFnZLcS39</picture>
      <picture>https://lh3.googleusercontent.com/d/1USwwg_NvQ7QQ4Dx9CLj6QXQP15Ay34_u</picture>
      <picture>https://lh3.googleusercontent.com/d/1X_7tQYV-goFslD3lQdFX86jePs2mNNa_</picture>
      <description>Пачки — новый формат для тех, кто хочет максимум свежести и аромата. Свежесрезанные цветы прямо из теплицы: без услуг флориста и лишней упаковки — выгодно и просто. Формат: пачка 25 стеблей; можно заказать несколько пачек. Открытка, сборка букета и добавление отдельных стеблей не предусмотрены. *Цветы доставляются без дополнительной обработки флористом — сохраняем их естественный вид.</description>
      <param name="Высота, см">55</param>
      <param name="Ширина, см">15</param>
      <param name="Страна">Голландия</param>
      <param name="Производитель">Zentoo</param>
      <param name="Артикул">Va0105c</param>
      <consist name="Хризантема Сантини Росси Пинк" unit="шт">25</consist>
    </offer>
    <offer id="Va3716c" available="true">
      <name>Пачка (10 шт.) Вибурнум Зеленый 60 см Арт. Va3716c</name>
      <categoryId>450</categoryId>
      <price>5219</price>
      <qty>8</qty>
      <picture>https://lh3.googleusercontent.com/d/1Pl2G78h6KXoy0y1OzbGrO275kDGHKDTz</picture>
      <picture>https://lh3.googleusercontent.com/d/1GTRouOlSYm4qlD8sOQPBSiXhx9wBvIfp</picture>
      <picture>https://lh3.googleusercontent.com/d/1aSoaRP6kuFrOX3ivTwE7e30DuOaapApH</picture>
      <description>Пачки — новый формат для тех, кто хочет максимум свежести и аромата. Свежесрезанные цветы прямо из теплицы: без услуг флориста и лишней упаковки — выгодно и просто. Формат: пачка 10 стеблей; можно заказать несколько пачек. Открытка, сборка букета и добавление отдельных стеблей не предусмотрены. *Цветы доставляются без дополнительной обработки флористом — сохраняем их естественный вид.</description>
      <param name="Высота, см">60</param>
      <param name="Ширина, см">15</param>
      <param name="Страна">уточняется</param>
      <param name="Артикул">Va3716c</param>
      <consist name="Вибурнум" unit="шт">10</consist>
    </offer>
    <offer id="Va1627c" available="true">
      <name>Пачка (25 шт.) Гвоздика одноголовая Красный 70 см Арт. Va1627c</name>
      <categoryId>450</categoryId>
      <price>2983</price>
      <qty>5</qty>
      <picture>https://lh3.googleusercontent.com/d/1uPh6PuFGIEPQrf-T_rbBi1N1yCh6bVwJ</picture>
      <picture>https://lh3.googleusercontent.com/d/13UK4S67Knzhwq9gMvAU5gkxuOVyRiphi</picture>
      <picture>https://lh3.googleusercontent.com/d/1Yl8ZhuImcs9fOgxou1r3cU341qDGmUpF</picture>
      <description>Пачки — новый формат для тех, кто хочет максимум свежести и аромата. Свежесрезанные цветы прямо из теплицы: без услуг флориста и лишней упаковки — выгодно и просто. Формат: пачка 25 стеблей; можно заказать несколько пачек. Открытка, сборка букета и добавление отдельных стеблей не предусмотрены. *Цветы доставляются без дополнительной обработки флористом — сохраняем их естественный вид.</description>
      <param name="Высота, см">70</param>
      <param name="Ширина, см">15</param>
      <param name="Страна">уточняется</param>
      <param name="Артикул">Va1627c</param>
      <consist name="Гвоздика одноголовая" unit="шт">25</consist>
    </offer>
    <offer id="Va2197c" available="true">
      <name>Пачка (25 шт.) Гвоздика одноголовая Красный 70 см Арт. Va2197c</name>
      <categoryId>450</categoryId>
      <price>2983</price>
      <qty>4</qty>
      <picture>https://lh3.googleusercontent.com/d/1r8z4KqNfPsJu29m8fUvAgPK6Y3maKDZ5</picture>
      <picture>https://lh3.googleusercontent.com/d/1C2mXeJXSsF0eHdDPCqPF9r0dOjVhEdQW</picture>
      <picture>https://lh3.googleusercontent.com/d/1LUVMxG2o9UzEJA7gnN4MIllLLU-e94PP</picture>
      <description>Пачки — новый формат для тех, кто хочет максимум свежести и аромата. Свежесрезанные цветы прямо из теплицы: без услуг флориста и лишней упаковки — выгодно и просто. Формат: пачка 25 стеблей; можно заказать несколько пачек. Открытка, сборка букета и добавление отдельных стеблей не предусмотрены. *Цветы доставляются без дополнительной обработки флористом — сохраняем их естественный вид.</description>
      <param name="Высота, см">70</param>
      <param name="Ширина, см">15</param>
      <param name="Страна">уточняется</param>
      <param name="Артикул">Va2197c</param>
      <consist name="Гвоздика одноголовая" unit="шт">25</consist>
    </offer>
    <offer id="Va1335c" available="true">
      <name>Пачка (10 шт.) Гиперикум Коко Диабло 50 см Арт. Va1335c</name>
      <categoryId>450</categoryId>
      <price>2135</price>
      <qty>8</qty>
      <picture>https://lh3.googleusercontent.com/d/1CeAjq9AhtQ0P8oz45APysHEZC9dVKrCJ</picture>
      <picture>https://lh3.googleusercontent.com/d/1-hIS2Z5a43dm76Lp4PVWqHOeNe9qjUqy</picture>
      <picture>https://lh3.googleusercontent.com/d/1k7D626AW6dJIO5FLTyIni4ad8pZFVl1m</picture>
      <description>Пачки — новый формат для тех, кто хочет максимум свежести и аромата. Свежесрезанные цветы прямо из теплицы: без услуг флориста и лишней упаковки — выгодно и просто. Формат: пачка 10 стеблей; можно заказать несколько пачек. Открытка, сборка букета и добавление отдельных стеблей не предусмотрены. *Цветы доставляются без дополнительной обработки флористом — сохраняем их естественный вид.</description>
      <param name="Высота, см">50</param>
      <param name="Ширина, см">15</param>
      <param name="Страна">Кения</param>
      <param name="Производитель">Florius Flowers</param>
      <param name="Артикул">Va1335c</param>
      <consist name="Гиперикум Коко Диабло" unit="шт">10</consist>
    </offer>
    <offer id="Va0175c" available="true">
      <name>Пачка (10 шт.) Гиперикум Коко Казино 50 см Арт. Va0175c</name>
      <categoryId>450</categoryId>
      <price>2135</price>
      <qty>7</qty>
      <picture>https://lh3.googleusercontent.com/d/1kdrxBpiet9Pjvr0sbFxz2xT6tuthbPoh</picture>
      <picture>https://lh3.googleusercontent.com/d/1qnW_ZyP33LDkvGF1EHfb9Q5yAKn7HRNL</picture>
      <picture>https://lh3.googleusercontent.com/d/1EIehR1MNRmLKhPSjTqrj-GRV2V89NR2r</picture>
      <description>Пачки — новый формат для тех, кто хочет максимум свежести и аромата. Свежесрезанные цветы прямо из теплицы: без услуг флориста и лишней упаковки — выгодно и просто. Формат: пачка 10 стеблей; можно заказать несколько пачек. Открытка, сборка букета и добавление отдельных стеблей не предусмотрены. *Цветы доставляются без дополнительной обработки флористом — сохраняем их естественный вид.</description>
      <param name="Высота, см">50</param>
      <param name="Ширина, см">15</param>
      <param name="Страна">Кения</param>
      <param name="Производитель">Florius Flowers</param>
      <param name="Артикул">Va0175c</param>
      <consist name="Гиперикум Коко Казино" unit="шт">10</consist>
    </offer>
    <offer id="Va0165c" available="true">
      <name>Пачка (10 шт.) Гиперикум Коко Уно 50 см Арт. Va0165c</name>
      <categoryId>450</categoryId>
      <price>2135</price>
      <qty>10</qty>
      <picture>https://lh3.googleusercontent.com/d/1UPV00CQhh6uw2WRkPytSeeL8KnVsj0pE</picture>
      <picture>https://lh3.googleusercontent.com/d/1OJaNIBwG3KuQCSYldlp9EUEPPtc4ET5f</picture>
      <picture>https://lh3.googleusercontent.com/d/1Biif_ol26mxiqJQUzvE_4ZSTFXRrid5C</picture>
      <description>Пачки — новый формат для тех, кто хочет максимум свежести и аромата. Свежесрезанные цветы прямо из теплицы: без услуг флориста и лишней упаковки — выгодно и просто. Формат: пачка 10 стеблей; можно заказать несколько пачек. Открытка, сборка букета и добавление отдельных стеблей не предусмотрены. *Цветы доставляются без дополнительной обработки флористом — сохраняем их естественный вид.</description>
      <param name="Высота, см">50</param>
      <param name="Ширина, см">15</param>
      <param name="Страна">Кения</param>
      <param name="Производитель">Florius Flowers</param>
      <param name="Артикул">Va0165c</param>
      <consist name="Гиперикум Коко Уно" unit="шт">10</consist>
    </offer>
    <offer id="Va1376c" available="true">
      <name>Пачка (10 шт.) Калла Белый 60 см Арт. Va1376c</name>
      <categoryId>450</categoryId>
      <price>3843</price>
      <qty>8</qty>
      <picture>https://lh3.googleusercontent.com/d/19RzHNW-HxPjoWzw1EgZRVKM43evtu5w9</picture>
      <picture>https://lh3.googleusercontent.com/d/1nFNBNbAZGvVMoW_-d76P68xizbvZjHHE</picture>
      <picture>https://lh3.googleusercontent.com/d/1CqA2-djjNJVVwZTZVCsOenktYt7gbeB0</picture>
      <description>Пачки — новый формат для тех, кто хочет максимум свежести и аромата. Свежесрезанные цветы прямо из теплицы: без услуг флориста и лишней упаковки — выгодно и просто. Формат: пачка 10 стеблей; можно заказать несколько пачек. Открытка, сборка букета и добавление отдельных стеблей не предусмотрены. *Цветы доставляются без дополнительной обработки флористом — сохраняем их естественный вид.</description>
      <param name="Высота, см">60</param>
      <param name="Ширина, см">15</param>
      <param name="Страна">Голландия</param>
      <param name="Производитель">Decorum</param>
      <param name="Артикул">Va1376c</param>
      <consist name="Калла" unit="шт">10</consist>
    </offer>
    <offer id="Va2754c" available="true">
      <name>Пачка (10 шт.) Клематис Лиловый 40 см Арт. Va2754c</name>
      <categoryId>450</categoryId>
      <price>3264</price>
      <qty>2</qty>
      <picture>https://lh3.googleusercontent.com/d/1g5mBx0tI8dMQNrlQBOlT0YqO04gmTkpd</picture>
      <picture>https://lh3.googleusercontent.com/d/1AlODWkxanwGqBtJdXgqfQzsOwDM-zEX-</picture>
      <picture>https://lh3.googleusercontent.com/d/1F53nvwYMksv74FcEjRh4eZJSbdrQPhGw</picture>
      <description>Пачки — новый формат для тех, кто хочет максимум свежести и аромата. Свежесрезанные цветы прямо из теплицы: без услуг флориста и лишней упаковки — выгодно и просто. Формат: пачка 10 стеблей; можно заказать несколько пачек. Открытка, сборка букета и добавление отдельных стеблей не предусмотрены. *Цветы доставляются без дополнительной обработки флористом — сохраняем их естественный вид.</description>
      <param name="Высота, см">40</param>
      <param name="Ширина, см">15</param>
      <param name="Страна">Голландия</param>
      <param name="Производитель">Marginpar</param>
      <param name="Артикул">Va2754c</param>
      <consist name="Клематис" unit="шт">10</consist>
    </offer>
    <offer id="Va2496c" available="true">
      <name>Пачка (10 шт.) Маттиола Фуксия 60 см Арт. Va2496c</name>
      <categoryId>450</categoryId>
      <price>3243</price>
      <qty>8</qty>
      <picture>https://lh3.googleusercontent.com/d/1fd1A8P2yJemBUIpSnmJdOj6y-Jm5qmSn</picture>
      <picture>https://lh3.googleusercontent.com/d/1-e-NTd1KyIMVYC0o0HFi5rf_ujX9sAi3</picture>
      <picture>https://lh3.googleusercontent.com/d/1w3-5EQj5_4yOfb2TyyMljenYQq2_AhUt</picture>
      <description>Пачки — новый формат для тех, кто хочет максимум свежести и аромата. Свежесрезанные цветы прямо из теплицы: без услуг флориста и лишней упаковки — выгодно и просто. Формат: пачка 10 стеблей; можно заказать несколько пачек. Открытка, сборка букета и добавление отдельных стеблей не предусмотрены. *Цветы доставляются без дополнительной обработки флористом — сохраняем их естественный вид.</description>
      <param name="Высота, см">60</param>
      <param name="Ширина, см">15</param>
      <param name="Страна">Италия</param>
      <param name="Производитель">Iblaflor</param>
      <param name="Артикул">Va2496c</param>
      <consist name="Маттиола" unit="шт">10</consist>
    </offer>
    <offer id="Va3146c" available="true">
      <name>Пачка (10 шт.) Маттиола Фиолетовый 60 см Арт. Va3146c</name>
      <categoryId>450</categoryId>
      <price>3243</price>
      <qty>5</qty>
      <picture>https://lh3.googleusercontent.com/d/1coSQf9IT40UGkBg4j9cFwpea4bIV0qR2</picture>
      <picture>https://lh3.googleusercontent.com/d/1-74akUt1v_GEPs7nw639hz7fB1ux5JGA</picture>
      <picture>https://lh3.googleusercontent.com/d/1JxuRsfFd1aZwTQZNo4somtnhQfzcLjpg</picture>
      <description>Пачки — новый формат для тех, кто хочет максимум свежести и аромата. Свежесрезанные цветы прямо из теплицы: без услуг флориста и лишней упаковки — выгодно и просто. Формат: пачка 10 стеблей; можно заказать несколько пачек. Открытка, сборка букета и добавление отдельных стеблей не предусмотрены. *Цветы доставляются без дополнительной обработки флористом — сохраняем их естественный вид.</description>
      <param name="Высота, см">60</param>
      <param name="Ширина, см">15</param>
      <param name="Страна">уточняется</param>
      <param name="Артикул">Va3146c</param>
      <consist name="Маттиола" unit="шт">10</consist>
    </offer>
    <offer id="Va2484c" available="true">
      <name>Пачка (50 шт.) Тюльпан пионовидный Фиолетовый 40 см Арт. Va2484c</name>
      <categoryId>450</categoryId>
      <price>7983</price>
      <qty>2</qty>
      <picture>https://lh3.googleusercontent.com/d/1oz7Yqz4mRWz_jNDatHWqQprn0IAZKbX8</picture>
      <picture>https://lh3.googleusercontent.com/d/1Bzsq7DdlDRIaIlH5Im_lH561k_yoLTD3</picture>
      <picture>https://lh3.googleusercontent.com/d/1zWMyMysKzmbDB0fNqf4RsZai_uESK1QD</picture>
      <description>Рекомендации по уходу за тюльпанами в пачке: не снимая упаковку подрежьте тюльпаны ровным срезом и поставьте в холодную воду. Через 5-6 часов упаковку можно снять. Пачки — новый формат для тех, кто хочет максимум свежести и аромата. Свежесрезанные цветы прямо из теплицы: без услуг флориста и лишней упаковки — выгодно и просто. Формат: пачка 50 стеблей; можно заказать несколько пачек. Открытка, сборка букета и добавление отдельных стеблей не предусмотрены. *Цветы доставляются без дополнительной обработки флористом — сохраняем их естественный вид.</description>
      <param name="Высота, см">40</param>
      <param name="Ширина, см">15</param>
      <param name="Страна">Голландия</param>
      <param name="Артикул">Va2484c</param>
      <consist name="Тюльпан пионовидный" unit="шт">50</consist>
    </offer>
    <offer id="Va3984c" available="true">
      <name>Пачка (50 шт.) Тюльпан пионовидный 40 см Арт. Va3984c</name>
      <categoryId>450</categoryId>
      <price>7983</price>
      <qty>2</qty>
      <picture>https://lh3.googleusercontent.com/d/1OXckH57p23aI0xWtRAfIqGpLF2_e7G3p</picture>
      <picture>https://lh3.googleusercontent.com/d/17xQQmz3MyAGEdp_7hWsUAWujHevcfAnL</picture>
      <picture>https://lh3.googleusercontent.com/d/1uoFfOGWtI3-_9zak4EEgU6kNGtwd8THe</picture>
      <description>Рекомендации по уходу за тюльпанами в пачке: не снимая упаковку подрежьте тюльпаны ровным срезом и поставьте в холодную воду. Через 5-6 часов упаковку можно снять. Пачки — новый формат для тех, кто хочет максимум свежести и аромата. Свежесрезанные цветы прямо из теплицы: без услуг флориста и лишней упаковки — выгодно и просто. Формат: пачка 50 стеблей; можно заказать несколько пачек. Открытка, сборка букета и добавление отдельных стеблей не предусмотрены. *Цветы доставляются без дополнительной обработки флористом — сохраняем их естественный вид.</description>
      <param name="Высота, см">40</param>
      <param name="Ширина, см">15</param>
      <param name="Страна">Голландия</param>
      <param name="Артикул">Va3984c</param>
      <consist name="Тюльпан пионовидный" unit="шт">50</consist>
    </offer>
    <offer id="Va4154c" available="true">
      <name>Пачка (50 шт.) Тюльпан пионовидный 40 см Арт. Va4154c</name>
      <categoryId>450</categoryId>
      <price>7983</price>
      <qty>2</qty>
      <picture>https://lh3.googleusercontent.com/d/1NbWeK0v8R1-o0jMgd-8mLqKYRfXD6b8f</picture>
      <picture>https://lh3.googleusercontent.com/d/1XtwOMIrWCqM6V9h3L7WSbkWbbLIU3iho</picture>
      <picture>https://lh3.googleusercontent.com/d/1hIsq7RXqgD-qqmv2aHgavSQhrWcmOVOQ</picture>
      <description>Рекомендации по уходу за тюльпанами в пачке: не снимая упаковку подрежьте тюльпаны ровным срезом и поставьте в холодную воду. Через 5-6 часов упаковку можно снять. Пачки — новый формат для тех, кто хочет максимум свежести и аромата. Свежесрезанные цветы прямо из теплицы: без услуг флориста и лишней упаковки — выгодно и просто. Формат: пачка 50 стеблей; можно заказать несколько пачек. Открытка, сборка букета и добавление отдельных стеблей не предусмотрены. *Цветы доставляются без дополнительной обработки флористом — сохраняем их естественный вид.</description>
      <param name="Высота, см">40</param>
      <param name="Ширина, см">15</param>
      <param name="Страна">Голландия</param>
      <param name="Артикул">Va4154c</param>
      <consist name="Тюльпан пионовидный" unit="шт">50</consist>
    </offer>
    <offer id="Va4184c" available="true">
      <name>Пачка (50 шт.) Тюльпан пионовидный Самбука 40 см Арт. Va4184c</name>
      <categoryId>450</categoryId>
      <price>7983</price>
      <qty>2</qty>
      <picture>https://lh3.googleusercontent.com/d/1mGaNnEW33yaoJB210m57S4aCNEhNGoFv</picture>
      <picture>https://lh3.googleusercontent.com/d/1pBTzugxaei2s9Qmc7qzd-3ME2STTyDfT</picture>
      <picture>https://lh3.googleusercontent.com/d/1YznGTTuiEb2zUfzYaxITRNDUFdRwBBw3</picture>
      <description>Рекомендации по уходу за тюльпанами в пачке: не снимая упаковку подрежьте тюльпаны ровным срезом и поставьте в холодную воду. Через 5-6 часов упаковку можно снять. Пачки — новый формат для тех, кто хочет максимум свежести и аромата. Свежесрезанные цветы прямо из теплицы: без услуг флориста и лишней упаковки — выгодно и просто. Формат: пачка 50 стеблей; можно заказать несколько пачек. Открытка, сборка букета и добавление отдельных стеблей не предусмотрены. *Цветы доставляются без дополнительной обработки флористом — сохраняем их естественный вид.</description>
      <param name="Высота, см">40</param>
      <param name="Ширина, см">15</param>
      <param name="Страна">уточняется</param>
      <param name="Артикул">Va4184c</param>
      <consist name="Тюльпан пионовидный Самбука" unit="шт">50</consist>
    </offer>
    <offer id="Va1306c" available="true">
      <name>Пачка (50 шт.) Фрезия Белый 60 см Арт. Va1306c</name>
      <categoryId>450</categoryId>
      <price>10447</price>
      <qty>2</qty>
      <picture>https://lh3.googleusercontent.com/d/1CMj552WzG-T9WmMcUj4sCrSwLIdQvE9H</picture>
      <picture>https://lh3.googleusercontent.com/d/18WCHbxgzkR3jdT7-SxWct8BFKBG_yV6B</picture>
      <picture>https://lh3.googleusercontent.com/d/1ClcUlsSf_9McwSYq6n1p3GJKCS00Gzrq</picture>
      <description>Пачки — новый формат для тех, кто хочет максимум свежести и аромата. Свежесрезанные цветы прямо из теплицы: без услуг флориста и лишней упаковки — выгодно и просто. Формат: пачка 50 стеблей; можно заказать несколько пачек. Открытка, сборка букета и добавление отдельных стеблей не предусмотрены. *Цветы доставляются без дополнительной обработки флористом — сохраняем их естественный вид.</description>
      <param name="Высота, см">60</param>
      <param name="Ширина, см">15</param>
      <param name="Страна">уточняется</param>
      <param name="Артикул">Va1306c</param>
      <consist name="Фрезия" unit="шт">50</consist>
    </offer>
    </offers>
  </shop>
</yml_catalog>